tree_sitter_idl-3.13.0.dist-info/METADATA
tree_sitter_idl-3.13.0.dist-info/RECORD
tree_sitter_idl-3.13.0.dist-info/top_level.txt
tree_sitter_idl-3.13.0.dist-info/WHEEL
tree_sitter_idl-3.13.0.dist-info/licenses/LICENSE
tree_sitter_idl/__init__.py
tree_sitter_idl/binding.c
tree_sitter_idl/py.typed
tree_sitter_idl/__init__.pyi
tree_sitter_idl/_binding.abi3.so
tree_sitter_idl/queries/indents.scm
tree_sitter_idl/queries/injections.scm
tree_sitter_idl/queries/highlights.scm
