Metadata-Version: 2.4
Name: tree-sitter-idl
Version: 3.13.0
Summary: Idl grammar for tree-sitter
License: Apache-2.0
Project-URL: Homepage, https://github.com/cathaysia/tree-sitter-idl
Keywords: incremental,parsing,tree-sitter,idl
Classifier: Intended Audience :: Developers
Classifier: License :: OSI Approved :: Apache Software License
Classifier: Topic :: Software Development :: Compilers
Classifier: Topic :: Text Processing :: Linguistic
Classifier: Typing :: Typed
Requires-Python: >=3.8
License-File: LICENSE
Provides-Extra: core
Requires-Dist: tree-sitter~=0.21; extra == "core"
Dynamic: license-file
